MANIFEST.in
setup.py
include/apps/speller.h
include/etana/adhoc.h
include/etana/ahel2.h
include/etana/arva.h
include/etana/cmorf.h
include/etana/ctulem.h
include/etana/cxxbs3.h
include/etana/cxxcash.h
include/etana/etmrf.h
include/etana/etmrfana.h
include/etana/etmrfverstr.h
include/etana/f-info.h
include/etana/fsxstring.h
include/etana/ini_mrf.h
include/etana/kr6nksud.h
include/etana/lib_amor32_macprefix.h
include/etana/loefailist.h
include/etana/mittesona.h
include/etana/mrf-mrf.h
include/etana/mrf2yh2mrf.h
include/etana/mrflags.h
include/etana/pfscodepage.h
include/etana/post-fsc.h
include/etana/result.h
include/etana/rooma.h
include/etana/s6n0.h
include/etana/silp.h
include/etana/sloendid.h
include/etana/sonatk.h
include/etana/suurused.h
include/etana/tloendid.h
include/etana/tmk2t.h
include/etana/tmk2tx.h
include/etana/tmplarray.h
include/etana/tmplptrarrayblabla.h
include/etana/tmplptrsrtfnd.h
include/etana/tulem.h
include/etana/tyybid.h
include/etana/vabamorf.h
include/etana/viga.h
include/fsc/fsblockalloc.h
include/fsc/fsc.h
include/fsc/fscinit.h
include/fsc/fsdata.h
include/fsc/fsdll.h
include/fsc/fsexception.h
include/fsc/fsfile.h
include/fsc/fsfixalloc.h
include/fsc/fshugeinteger.h
include/fsc/fslist.h
include/fsc/fsmemory.h
include/fsc/fsreg.h
include/fsc/fssmartptr.h
include/fsc/fsstream.h
include/fsc/fsstring.h
include/fsc/fsstring2.h
include/fsc/fsthread.h
include/fsc/fstime.h
include/fsc/fstrace.h
include/fsc/fstype.h
include/fsc/fsutil.h
include/fsc/fsvar.h
include/fsc/fswav.h
include/fsc/stdfsc.h
include/fsc/fsjni/fsjni.h
include/json/json.h
include/proof/linguistic.h
include/proof/proof.h
include/proof/pttype.h
include/proof/ptword.h
include/proof/suggestor.h
pyvabamorf/__init__.py
pyvabamorf/morf.py
pyvabamorf/six.py
pyvabamorf/vabamorf.i
pyvabamorf/vabamorf.py
pyvabamorf.egg-info/PKG-INFO
pyvabamorf.egg-info/SOURCES.txt
pyvabamorf.egg-info/dependency_links.txt
pyvabamorf.egg-info/top_level.txt
pyvabamorf/dct/et.dct
pyvabamorf/tests/__init__.py
pyvabamorf/tests/test_analyze.py
pyvabamorf/tests/test_multi.py
pyvabamorf/tests/test_synthesize.py
src/etana/adhoc.cpp
