Metadata-Version: 1.1
Name: pyvabamorf
Version: 1.6
Summary: Python interface for the Vabamorf Estonian lemmatizer and morphological analyzer.
Home-page: https://github.com/brainscauseminds/pyvabamorf
Author: Tarmo Vaino, Heiki-Jaan Kaalep, Sven Laur, Timo Petmanson, Aleksandr Tkachenko, Siim Orasmaa, Raul Sirel
Author-email: tpetmanson@gmail.com
License: UNKNOWN
Platform: UNKNOWN
Classifier: Intended Audience :: Developers
Classifier: Intended Audience :: Education
Classifier: Intended Audience :: Science/Research
Classifier: Intended Audience :: Information Technology
Classifier: License :: OSI Approved :: GNU Library or Lesser General Public License (LGPL)
Classifier: Operating System :: OS Independent
Classifier: Topic :: Scientific/Engineering
Classifier: Topic :: Scientific/Engineering :: Artificial Intelligence
Classifier: Topic :: Scientific/Engineering :: Information Analysis
Classifier: Topic :: Text Processing
Classifier: Topic :: Text Processing :: Linguistic
